Workbook

Sheet PLANILLA DE PAGO
B1: Rubí del Valle
B2: Nomina Salarial Correspondiente Al Mes De Mayo Del 2026.
B3: Periodo del 01 al 30 de Mayo del 2026
B4: # INSS | C4: Datos Personales | E4: Cargo | F4: N° Cedúlas | G4: Ingresos | L4: Deducciones | Q4: Neto a Pagar | R4: Inss Patronal | S4: Inatec | T4: Prestaciones
C5: Nombre y Apellidos | G5: Salario Básico | H5: Comisiones | I5: Horas Extras | J5: Incentivos | K5: Total Ingresos | L5: Inss Laboral | M5: IR | N5: Embargo | O5: Sindicato | P5: Total Deducciones | T5: Vacaciones | U5: Aguinaldo | V5: Indemnización
C6: Anielka Del Socorro Sánchez Sequeira | E6: Administración | F6: 041-070102-1000L | G6: 12000 | H6: 0 | I6: 0 | J6: 0 | K6: =G6+J6+H6+I6 -> 12000 | L6: =K6*7% -> 840 | M6: ='Calculadora IR'!H10 -> 550 | N6: 0 | O6: 0 | P6: =L6+M6+N6+O6 -> 1390 | Q6: =K6-P6 -> 10610 | R6: =+K6*0.215 -> 2580 | S6: =+K6*0.02 -> 240 | T6: =G6/30*2.5 -> 1000 | U6: =G6/30*2.5 -> 1000 | V6: =G6/30*2.5 -> 1000
C7: Josepth Emanuel Mendieta Diaz | E7: Operario | F7: 001-150665-1023H | G7: 11080 | H7: 0 | I7: =G7/240*1.8*8 -> 664.8 | J7: 0 | K7: =G7+J7+H7+I7 -> 11744.8 | L7: =K7*7% -> 822.136 | M7: ='Calculadora IR'!H17 -> 412 | N7: 0 | O7: 0 | P7: =L7+M7+N7+O7 -> 1234.136 | Q7: =K7-P7 -> 10510.664 | R7: =+K7*0.215 -> 2525.132 | S7: =+K7*0.02 -> 234.896 | T7: =G7/30*2.5 -> 923.33333 | U7: =G7/30*2.5 -> 923.33333 | V7: =G7/30*2.5 -> 923.33333
C8: Haxel Alexander Navarro López | E8: Supervisor | F8: 002-220772-5045K | G8: 11000 | H8: 0 | I8: 0 | J8: 0 | K8: =G8+J8+H8+I8 -> 11000 | L8: =K8*7% -> 770 | M8: ='Calculadora IR'!H24 -> 400 | N8: 0 | O8: 0 | P8: =L8+M8+N8+O8 -> 1170 | Q8: =K8-P8 -> 9830 | R8: =+K8*0.215 -> 2365 | S8: =+K8*0.02 -> 220 | T8: =G8/30*2.5 -> 916.66667 | U8: =G8/30*2.5 -> 916.66667 | V8: =G8/30*2.5 -> 916.66667
C9: Monica Alejandra López Perez | E9: Vendedor | F9: 003-030380-6067L | G9: 9000 | H9: 0 | I9: =G9/240*1.5*8 -> 450 | J9: 0 | K9: =G9+J9+H9+I9 -> 9450 | L9: =K9*7% -> 661.5 | M9: ='Calculadora IR'!H31 -> 100 | N9: 0 | O9: 0 | P9: =L9+M9+N9+O9 -> 761.5 | Q9: =K9-P9 -> 8688.5 | R9: =+K9*0.215 -> 2031.75 | S9: =+K9*0.02 -> 189 | T9: =G9/30*2.5 -> 750 | U9: =G9/30*2.5 -> 750 | V9: =G9/30*2.5 -> 750
B10: Total | G10: =SUM(G6:G9) -> 43080 | H10: =SUM(H6:H9) -> 0 | I10: =SUM(I6:I9) -> 1114.8 | J10: =SUM(J6:J9) -> 0 | K10: =SUM(K6:K9) -> 44194.8 | L10: =SUM(L6:L9) -> 3093.636 | M10: =SUM(M6:M9) -> 1462 | N10: =SUM(N6:N9) -> 0 | ... V10: =SUM(V6:V9) -> 3590
F12: $ 74,790.00
F13: 74790 | G13: =F13-G10 -> 31710

Sheet COMPROBANTE CONTABLE
B1: Legado Vivo
B2: Comprobante Contable de Nómina
B3: Período del 01 al 30 de Mayo del 2026
B4: DESCRIPCION DE CUENTA | C4: DEBE | D4: HABER
B5: Salarios | C5: ='PLANILLA DE PAGO'!G10 -> 43080
B6: Horas extras | C6: ='PLANILLA DE PAGO'!I10 -> 1114.8
B7: Dias Feriados | C7: -
B8: Vacaciones | C8: ='PLANILLA DE PAGO'!T10 -> 3590
B9: Aguinaldo | C9: ='PLANILLA DE PAGO'!U10 -> 3590
B10: Indemnización | C10: ='PLANILLA DE PAGO'!V10 -> 3590
B11: Inss Patronal | C11: ='PLANILLA DE PAGO'!R10 -> 9501.882
B12: Inatec | C12: ='PLANILLA DE PAGO'!S10 -> 883.896
B13: Salarios por pagar | D13: ='PLANILLA DE PAGO'!Q10 -> 39639.164
B14: Inss Laboral por pagar | D14: ='PLANILLA DE PAGO'!L10 -> 3093.636
B15: Inss Patronal por Pagar | D15: ='PLANILLA DE PAGO'!R10 -> 9501.882
B16: Inatec por pagar | D16: ='PLANILLA DE PAGO'!S10 -> 883.896
B17: Ir por pagar | D17: ='PLANILLA DE PAGO'!M10 -> 1462
B18: Vacaciones por pagar | D18: ='PLANILLA DE PAGO'!T10 -> 3590
B19: Aguinaldo por pagar | D19: ='PLANILLA DE PAGO'!U10 -> 3590
B20: Indemnización por pagar | D20: ='PLANILLA DE PAGO'!V10 -> 3590
B21: Sumas Iguales | C21: =SUM(C5:C20) -> 65350.578 | D21: =SUM(D5:D20) -> 65350.578

Sheet Calculadora IR
A5: Tabla progresiva | G5: Calculadora de IR | K5: 12000
A6: De | B6: Hasta | C6: impuesto base | D6: porcentaje aplicable | E6: sobre exceso | G6: Sobre exceso | H6: =VLOOKUP(K5*12,A7:E11,E12,1) -> 100000 | K6: 11080
A7: 1 | B7: 100000 | C7: 0 | E7: 0 | G7: Alícuota | H7: =VLOOKUP(K5*12,A7:E11,D12,1) -> 0.15 | K7: 11000
A8: 100000.01 | B8: 200000 | C8: 0 | D8: 0.15 | E8: 100000 | G8: Impuesto base | H8: =VLOOKUP(K5*12,A7:E11,C12,1) -> 0 | K8: 9000
A9: 200000.01 | B9: 350000 | C9: 15000 | D9: 0.2 | E9: 200000
A10: 350000.01 | B10: 500000 | C10: 45000 | D10: 0.25 | E10: 350000 | G10: IR | H10: =((((K5*12)-H6)*H7)+H8)/12 -> 550
A11: 500000.01 | B11: a mas | C11: 82500 | D11: 0.3 | E11: 500000
A12: 1 | B12: 2 | C12: 3 | D12: 4 | E12: 5 | G12: Calculadora de IR
G13: Sobre exceso | H13: =VLOOKUP(K6*12,A7:E11,E12,1) -> 100000
G14: Alícuota | H14: =VLOOKUP(K6*12,A7:E11,D12,1) -> 0.15
G15: Impuesto base | H15: =VLOOKUP(K6*12,A7:E11,C12,1) -> 0
G17: IR | H17: =((((K6*12)-H13)*H14)+H15)/12 -> 412
G19: Calculadora de IR | J19: Calculadora de IR | M19: Calculadora de IR
G20: Sobre exceso | H20: =VLOOKUP(K7*12,A7:E11,E12,1) -> 100000 | J20: Sobre exceso | K20: =VLOOKUP(K10*12,A7:E11,E12,1) -> #N/A | M20: Sobre exceso | N20: =VLOOKUP(K12*12,A7:E11,E12,1) -> #N/A
G21: Alícuota | H21: =VLOOKUP(K7*12,A7:E11,D12,1) -> 0.15 | J21: Alícuota | K21: =VLOOKUP(K10*12,A7:E11,D12,1) -> #N/A | M21: Alícuota | N21: =VLOOKUP(K12*12,A7:E11,D12,1) -> #N/A
G22: Impuesto base | H22: =VLOOKUP(K7*12,A7:E11,C12,1) -> 0 | J22: Impuesto base | K22: =VLOOKUP(K10*12,A7:E11,C12,1) -> #N/A | M22: Impuesto base | N22: =VLOOKUP(K12*12,A7:E11,C12,1) -> #N/A
G24: IR | H24: =((((K7*12)-H20)*H21)+H22)/12 -> 400 | J24: IR | K24: =((((K10*12)-K20)*K21)+K22)/12 -> #N/A | M24: IR | N24: =((((K12*12)-N20)*N21)+N22)/12 -> #N/A
G26: Calculadora de IR | J26: Calculadora de IR | M26: Calculadora de IR
G27: Sobre exceso | H27: =VLOOKUP(K8*12,A7:E11,E12,1) -> 100000 | J27: Sobre exceso | K27: =VLOOKUP(K11*12,A7:E11,E12,1) -> #N/A | M27: Sobre exceso | N27: =VLOOKUP(K13*12,A7:E11,E12,1) -> #N/A
G28: Alícuota | H28: =VLOOKUP(K8*12,A7:E11,D12,1) -> 0.15 | J28: Alícuota | K28: =VLOOKUP(K11*12,A7:E11,D12,1) -> #N/A | M28: Alícuota | N28: =VLOOKUP(K13*12,A7:E11,D12,1) -> #N/A
G29: Impuesto base | H29: =VLOOKUP(K8*12,A7:E11,C12,1) -> 0 | J29: Impuesto base | K29: =VLOOKUP(K11*12,A7:E11,C12,1) -> #N/A | M29: Impuesto base | N29: =VLOOKUP(K13*12,A7:E11,C12,1) -> #N/A
G31: IR | H31: =((((K8*12)-H27)*H28)+H29)/12 -> 100 | J31: IR | K31: =((((K11*12)-K27)*K28)+K29)/12 -> #N/A | M31: IR | N31: =((((K13*12)-N27)*N28)+N29)/12 -> #N/A
G33: Calculadora de IR
G34: Sobre exceso | H34: =VLOOKUP(K9*12,A7:E11,E12,1) -> #N/A
G35: Alícuota | H35: =VLOOKUP(K9*12,A7:E11,D12,1) -> #N/A
G36: Impuesto base | H36: =VLOOKUP(K9*12,A7:E11,C12,1) -> #N/A
G38: IR | H38: =((((K9*12)-H34)*H35)+H36)/12 -> #N/A
